swap_env/__init__.py
swap_env/__main__.py
swap_env/cli.py
swap_env/dotenv_dir.py
swap_env/dotenv_files.py
swap_env-2.0.0.dist-info/METADATA
swap_env-2.0.0.dist-info/WHEEL
swap_env-2.0.0.dist-info/entry_points.txt
swap_env-2.0.0.dist-info/licenses/LICENSE
swap_env-2.0.0.dist-info/RECORD
