Metadata-Version: 2.4
Name: swap-env
Version: 2.0.0
Summary: A simple CLI for swapping between .env files
Project-URL: Repository, https://codeberg.org/benba/swap-env
Project-URL: Changelog, https://codeberg.org/benba/swap-env/src/branch/main/CHANGELOG.md
Author-email: Ben Berry-Allwood <benberryallwood@gmail.com>
License-File: LICENSE
Classifier: Environment :: Console
Classifier: Intended Audience :: Developers
Classifier: License :: OSI Approved :: MIT License
Classifier: Operating System :: OS Independent
Classifier: Programming Language :: Python
Classifier: Programming Language :: Python :: 3 :: Only
Classifier: Programming Language :: Python :: 3.10
Classifier: Programming Language :: Python :: 3.11
Classifier: Programming Language :: Python :: 3.12
Classifier: Programming Language :: Python :: 3.13
Classifier: Programming Language :: Python :: 3.14
Requires-Python: >=3.10
Requires-Dist: prompt-toolkit>=3.0.48
